LICENSE
MANIFEST.in
README.rst
setup.py
blog/__init__.py
blog/admin.py
blog/apps.py
blog/models.py
blog/tests.py
blog/urls.py
blog/views.py
blog/migrations/__init__.py
django_lecamit83_blog.egg-info/PKG-INFO
django_lecamit83_blog.egg-info/SOURCES.txt
django_lecamit83_blog.egg-info/dependency_links.txt
django_lecamit83_blog.egg-info/top_level.txt